LICENSE
README.md
setup.py
src/key_interactions_network.egg-info/PKG-INFO
src/key_interactions_network.egg-info/SOURCES.txt
src/key_interactions_network.egg-info/dependency_links.txt
src/key_interactions_network.egg-info/requires.txt
src/key_interactions_network.egg-info/top_level.txt
src/kin/__init__.py
src/kin/alternate_contacts.py
src/kin/msa_conversion.py
src/kin/msa_indexing.py
src/kin/msa_network.py
src/kin/pymol_projections.py
src/kin/sequences.py
src/kin/utils.py
src/kin/contacts/__init__.py
src/kin/contacts/cation_pi.py
src/kin/contacts/contact_analysis.py
src/kin/contacts/hbonds.py
src/kin/contacts/hydrophobic.py
src/kin/contacts/pi_pi.py
src/kin/contacts/salt_bridges.py
src/kin/contacts/utils.py
src/kin/contacts/van_der_waals.py