Metadata-Version: 2.1
Name: key-interactions-network
Version: 0.1.0
Summary: A python package to study conserved protein interaction networks
Home-page: https://github.com/kamerlinlab/KIN
Author: Dariia Yehorova, Rory Crean
Author-email: rory.crean@kemi.uu.se
Classifier: Programming Language :: Python :: 3
Classifier: Operating System :: OS Independent
Requires-Python: >=3.10
Provides-Extra: dev
License-File: LICENSE
